{
  "lastUpdated": "2024-01-15T10:30:00Z",
  "version": 1,
  "participants": [
    {
      "team": "Интенсив",
      "name": "Ксения Л.",
      "angle": 0,
      "timeLz": "00:00:00",
      "timeKz": "00:00:00",
      "laps": 0,
      "penalty_gates": 0,
      "penalty_fall": 0,
      "penalty_flip": 0
    },
    {
      "team": "Интенсив",
      "name": "Святослав Е.",
      "angle": 0,
      "timeLz": "00:00:00",
      "timeKz": "00:00:00",
      "laps": 0,
      "penalty_gates": 0,
      "penalty_fall": 0,
      "penalty_flip": 0
    },
    {
      "team": "Прорыв",
      "name": "Никита У.",
      "angle": 0,
      "timeLz": "00:00:00",
      "timeKz": "00:00:00",
      "laps": 0,
      "penalty_gates": 0,
      "penalty_fall": 0,
      "penalty_flip": 0
    },
    {
      "team": "Прорыв",
      "name": "Варя А.",
      "angle": 0,
      "timeLz": "00:00:00",
      "timeKz": "00:00:00",
      "laps": 0,
      "penalty_gates": 0,
      "penalty_fall": 0,
      "penalty_flip": 0
    },
    {
      "team": "Альфа",
      "name": "Дмитрий В.",
      "angle": 0,
      "timeLz": "00:00:00",
      "timeKz": "00:00:00",
      "laps": 0,
      "penalty_gates": 0,
      "penalty_fall": 0,
      "penalty_flip": 0
    },
    {
      "team": "Альфа",
      "name": "Иван Ф.",
      "angle": 0,
      "timeLz": "00:00:00",
      "timeKz": "00:00:00",
      "laps": 0,
      "penalty_gates": 0,
      "penalty_fall": 0,
      "penalty_flip": 0
    },
    {
      "team": "Стабильность",
      "name": "Савелий С.",
      "angle": 0,
      "timeLz": "00:00:00",
      "timeKz": "00:00:00",
      "laps": 0,
      "penalty_gates": 0,
      "penalty_fall": 0,
      "penalty_flip": 0
    },
    {
      "team": "Стабильность",
      "name": "Богдан Е.",
      "angle": 0,
      "timeLz": "00:00:00",
      "timeKz": "00:00:00",
      "laps": 0,
      "penalty_gates": 0,
      "penalty_fall": 0,
      "penalty_flip": 0
    },
    {
      "team": "Мотивация",
      "name": "Артем П.",
      "angle": 0,
      "timeLz": "00:00:00",
      "timeKz": "00:00:00",
      "laps": 0,
      "penalty_gates": 0,
      "penalty_fall": 0,
      "penalty_flip": 0
    },
    {
      "team": "Мотивация",
      "name": "Данила Л.",
      "angle": 0,
      "timeLz": "00:00:00",
      "timeKz": "00:00:00",
      "laps": 0,
      "penalty_gates": 0,
      "penalty_fall": 0,
      "penalty_flip": 0
    }
  ]
}
